moonsdk/__init__.py
moonsdk/api/__init__.py
moonsdk/api/aave_api.py
moonsdk/api/accounts_api.py
moonsdk/api/bitcoin_api.py
moonsdk/api/bitcoincash_api.py
moonsdk/api/conveyor_finance_api.py
moonsdk/api/cosmos_api.py
moonsdk/api/default_api.py
moonsdk/api/doge_coin_api.py
moonsdk/api/ens_api.py
moonsdk/api/eos_api.py
moonsdk/api/erc1155_api.py
moonsdk/api/erc20_api.py
moonsdk/api/erc721_api.py
moonsdk/api/litecoin_api.py
moonsdk/api/oneinch_api.py
moonsdk/api/onramper_api.py
moonsdk/api/ripple_api.py
moonsdk/api/solana_api.py
moonsdk/api/tron_api.py
moonsdk/api/uni_swap_api.py
moonsdk/api/yearn_api.py
moonsdk/api_client.py
moonsdk/api_response.py
moonsdk/configuration.py
moonsdk/exceptions.py
moonsdk/models/__init__.py
moonsdk/models/aave_input.py
moonsdk/models/aave_reserves_api_response.py
moonsdk/models/aave_reserves_data.py
moonsdk/models/account_api_response.py
moonsdk/models/account_data.py
moonsdk/models/account_response.py
moonsdk/models/available_payment_method.py
moonsdk/models/balance_api_response.py
moonsdk/models/balance_response.py
moonsdk/models/bitcoin_api_response.py
moonsdk/models/bitcoin_cash_api_response.py
moonsdk/models/bitcoin_cash_input.py
moonsdk/models/bitcoin_cash_transaction_input.py
moonsdk/models/bitcoin_cash_transaction_output.py
moonsdk/models/bitcoin_input.py
moonsdk/models/bitcoin_transaction_input.py
moonsdk/models/bitcoin_transaction_output.py
moonsdk/models/broad_cast_raw_transaction_api_response.py
moonsdk/models/broad_cast_raw_transaction_response.py
moonsdk/models/broadcast_input.py
moonsdk/models/conveyor_finance_controller_response.py
moonsdk/models/cosmos_api_response.py
moonsdk/models/cosmos_input.py
moonsdk/models/cosmos_transaction_input.py
moonsdk/models/cosmos_transaction_output.py
moonsdk/models/create_account_input.py
moonsdk/models/crypto_currency.py
moonsdk/models/deploy_input.py
moonsdk/models/doge_coin_api_response.py
moonsdk/models/doge_coin_input.py
moonsdk/models/doge_coin_transaction_input.py
moonsdk-1.0.2.dist-info/METADATA
moonsdk-1.0.2.dist-info/WHEEL
moonsdk-1.0.2.dist-info/RECORD
