Metadata-Version: 2.1
Name: moonsdk
Version: 1.0.2
Summary: moon-vault-api
Home-page: https://github.com/moon-up/moon-sdk-python
License: ISC
Keywords: OpenAPI,OpenAPI-Generator,moon-vault-api
Author: OpenAPI Generator Community
Author-email: team@openapitools.org
Requires-Python: >=3.7,<4.0
Classifier: License :: OSI Approved
Classifier: Programming Language :: Python :: 3
Classifier: Programming Language :: Python :: 3.7
Classifier: Programming Language :: Python :: 3.8
Classifier: Programming Language :: Python :: 3.9
Classifier: Programming Language :: Python :: 3.10
Classifier: Programming Language :: Python :: 3.11
Classifier: Programming Language :: Python :: 3.12
Requires-Dist: aiohttp (>=3.8.4)
Requires-Dist: aiohttp-retry (>=2.8.3)
Requires-Dist: pydantic (>=2)
Requires-Dist: python-dateutil (>=2.8.2)
Requires-Dist: typing-extensions (>=4.7.1)
Requires-Dist: urllib3 (>=1.25.3)
Project-URL: Repository, https://github.com/moon-up/moon-sdk-python
